setup.py
email/_encoded_words.py
email/_parseaddr.py
email/_policybase.py
micropython_email.internal.egg-info/PKG-INFO
micropython_email.internal.egg-info/SOURCES.txt
micropython_email.internal.egg-info/dependency_links.txt
micropython_email.internal.egg-info/requires.txt
micropython_email.internal.egg-info/top_level.txt